Workbook

Sheet Feature Log
A1: FEATURE LOG - ECOS DEL GRIMORIO (actualizado al Sprint 2)
A2: Los features 1 a 14 vienen del Feature Log inicial (GDD 3.1); del 15 al 26 se agregaron en el Sprint 2 para cubrir secciones del GDD que no tenían feature; el 27 salió de las pruebas.
A3: Featureid | B3: Nombre | C3: Estado | D3: Días | E3: Sprintid | F3: Comentarios
A4: 1 | B4: Movimiento y salto del jugador | C4: Terminado | D4: 3 | E4: 2 | F4: PlayerController.cs: aceleración, coyote time, búfer de salto, esquive, agacharse y planeo
A5: 2 | B5: Sistema de maná y hechizo Arcano | C5: Terminado | D5: 4 | E5: 2 | F5: SpellCaster.cs + SpellData.cs; tres espacios de hechizo
A6: 3 | B6: IA de patrulla/persecución básica | C6: Terminado | D6: 3 | E6: 2 | F6: EnemyBase.cs → EnemyAI, FlyingEnemyAI, RangedEnemyAI
A7: 4 | B7: Sistema de vida (jugador/enemigos) | C7: Terminado | D7: 2 | E7: 2 | F7: Health.cs + IDamageable, resistencias por elemento
A8: 5 | B8: Hechizo de Fuego y combo Explosión Arcana | C8: Terminado | D8: 5 | E8: 2 | F8: Se adelantó al Sprint 2
A9: 6 | B9: Ala de Fuego completa con jefe Kaelor (Nivel 2) | C9: Terminado | D9: 6 | E9: 2 | F9: KaelorBoss.cs, 2 fases
A10: 7 | B10: Hechizo de Hielo y combo Vapor Cegador | C10: Terminado | D10: 4 | E10: 2 | F10: Congela al tercer golpe (2.11)
A11: 8 | B11: Ala de Hielo completa con jefa Isolde (Nivel 3) | C11: Terminado | D11: 6 | E11: 2 | F11: IsoldeBoss.cs, congela el suelo
A12: 9 | B12: Hechizo de Viento y combos Granizo Cortante / Tormenta de Ascuas | C12: Terminado | D12: 5 | E12: 2 | F12: Planeado para Sprint 3, se adelantó
A13: 10 | B13: Ala de Viento completa con jefe Threnody y plataformas móviles (Nivel 4) | C13: Terminado | D13: 7 | E13: 2 | F13: Planeado para Sprint 3, se adelantó
A14: 11 | B14: Corazón del Grimorio: Ecos Menores, Guardián Espejo y jefe final multifase (Nivel 5) | C14: Terminado | D14: 8 | E14: 2 | F14: ElenoraBoss.cs, 4 fases + final. Final del juego corregido el 7 de octubre
A15: 12 | B15: Sistema de Logros (AchievementManager basado en eventos) | C15: Terminado | D15: 3 | E15: 2 | F15: 10 logros, se adelantó del Sprint 4
A16: 13 | B16: Sistema de truco / Easter egg (Modo Archimaga) | C16: Terminado | D16: 2 | E16: 2 | F16: Teclado F-H-V-A + Enter; control L1 + R1 + Triángulo
A17: 14 | B17: Integración final, pulido y Gold Master | C17: En desarrollo | D17: 5 | E17: 3-4 | F17: Pruebas Alfa en curso; Beta y Gold Master en Sprints 3 y 4
A18: 15 | B18: Menú principal, pausa, Game Over y guardado (2.4, 2.5, 2.6) | C18: Terminado | D18: 3 | E18: 2 | F18: Agregado en Sprint 2 desde el GDD
A19: 16 | B19: Pantalla de Opciones (2.5, 2.6) | C19: Terminado | D19: 1 | E19: 2 | F19: Volumen de música, efectos y voces, pantalla completa y vibración
A20: 17 | B20: HUD y pantalla de resultados por ala (2.6) | C20: Terminado | D20: 2 | E20: 2 | F20: Tiempo, enemigos, daño, páginas, secretos
A21: 18 | B21: Historia: prólogo, diálogos, epílogo y créditos (2.14) | C21: Terminado | D21: 3 | E21: 2 | F21: Prologo.cs, NPCDialogue.cs, CreditsScreen.cs
A22: 19 | B22: Música, efectos de sonido y voces (2.17) | C22: Terminado | D22: 3 | E22: 2 | F22: 9 pistas, 41 efectos (12 agregados el 15 oct) y voces por personaje
A23: 20 | B23: Control de PS4 / Xbox y vibración (2.4) | C23: Terminado | D23: 1 | E23: 2 | F23: New Input System
A24: 21 | B24: Habilidades elementales y acertijos ambientales (2.1, 2.3, 2.11) | C24: Terminado | D24: 2 | E24: 2 | F24: Zarzas, muros de hielo, cajas, placas y puertas rúnicas
A25: 22 | B25: Armas de los enemigos (2.12) | C25: Terminado | D25: 1 | E25: 2 | F25: ArmaEnemigo.cs: Garras, Lanza, Embestida
A26: 23 | B26: Ítems, coleccionables y salas secretas (2.8, 2.13) | C26: Terminado | D26: 2 | E26: 2 | F26: Páginas Perdidas, vasijas, cofres y fragmentos
A27: 24 | B27: Build del juego para Windows (.exe) (5.1) | C27: En desarrollo | D27: 1 | E27: 2-3 | F27: Menú Ecos del Grimorio > Compilar juego (.exe). Primera compilación el 13 oct y versión 1.0 el 20 oct; falta probarlo en otra computadora
A28: 25 | B28: Documentación del Producto 2 (producción y evidencias) | C28: Terminado | D28: 2 | E28: 2 | F28: Documento Word/PDF, manual del jugador y este libro de Excel
A29: 26 | B29: Pruebas Beta y reporte Postmortem | C29: Planeado | D29: 6 | E29: 3-4 | F29: Jugadores externos; plantilla de Postmortem de Huddle
A30: 27 | B30: Ayudas al jugador: ayuda para apuntar, sentido arcano y saltar nivel | C30: Terminado | D30: 2 | E30: 2 | F30: Agregado después de las pruebas del 14 y 15 de octubre y de la revisión en clase

Sheet Sprint Plan
A1: SPRINT PLAN - ECOS DEL GRIMORIO (replaneado en el Sprint 2)
A2: Cambio respecto al plan inicial: los features 9 a 13 (Ala de Viento, Corazón del Grimorio, Logros y Modo Archimaga) se adelantaron al Sprint 2.
A3: Sprintid | B3: Inicio | C3: Días | D3: Fin | E3: Estado | F3: Meta | G3: Entrega
A4: 1 | B4: 46266 | C4: =D4-B4+1 -> 18 | D4: 46283 | E4: Terminado | F4: Preproducción y arte: GDD, bocetos, arte conceptual de personajes, enemigos, fondos, ítems y UI. | G4: Producto 1 (18 sep)
A5: 2 | B5: 46284 | C5: =D5-B5+1 -> 42 | D5: 46325 | E5: En desarrollo | F5: Juego completo jugable en Unity: 5 alas, 4 guardianes y jefe final, logros, Modo Archimaga, opciones, resultados, música y voces. Pruebas Alfa. | G5: Producto 2 (30 oct)
A6: 3 | B6: 46326 | C6: =D6-B6+1 -> 21 | D6: 46346 | E6: Planeado | F6: Pruebas Beta (cerradas y abiertas), balance de dificultad, corrección de bugs y borrador del Postmortem. | G6: Producto 3 (20 nov)
A7: 4 | B7: 46347 | C7: =D7-B7+1 -> 10 | D7: 46356 | E7: Planeado | F7: Gold Master: build final, Postmortem completo y entrega. | G7: Gold Master (30 nov)

Sheet Sprint Backlog
A1: SPRINT BACKLOG - SPRINT 2 (19 sep - 30 oct, 2026)
A2: Fin = día en que la tarea quedó terminada. Las gráficas de Burn-down y Task Chart se calculan con estas columnas.
A3: TaskID | B3: Featureid | C3: Nombre de la tarea | D3: Miembro | E3: Rol | F3: Estado | G3: Esfuerzo (hrs) | H3: Inicio | I3: Fin
A4: T01 | B4: 15 | C4: Ordenar sprites e importarlos a Unity (ConfigureSprites.cs) | D4: Alejandro Pérez Alcántara | E4: Programador | F4: Terminado | G4: 6 | H4: 46284 | I4: 46295
A5: T02 | B5: 2 | C5: ScriptableObjects SpellData, ItemData y EnemyData | D5: Alejandro Pérez Alcántara | E5: Programador | F5: Terminado | G5: 4 | H5: 46291 | I5: 46295
A6: T03 | B6: 1 | C6: PlayerController: movimiento, salto, coyote time, búfer y esquive | D6: Alejandro Pérez Alcántara | E6: Programador | F6: Terminado | G6: 8 | H6: 46291 | I6: 46295
A7: T04 | B7: 4 | C7: Health.cs, interfaz IDamageable y resistencias por elemento | D7: Alejandro Pérez Alcántara | E7: Programador | F7: Terminado | G7: 3 | H7: 46294 | I7: 46295
A8: T05 | B8: 2 | C8: SpellCaster: tres hechizos equipados, maná y tiempo de recarga | D8: Alejandro Pérez Alcántara | E8: Programador | F8: Terminado | G8: 6 | H8: 46294 | I8: 46295
A9: T06 | B9: 3 | C9: EnemyBase y herencia de IA (EnemyAI, FlyingEnemyAI, RangedEnemyAI) | D9: Alejandro Pérez Alcántara | E9: Programador | F9: Terminado | G9: 6 | H9: 46294 | I9: 46295
A10: T07 | B10: 15 | C10: GameManager con los estados del juego (2.5) y guardado | D10: Alejandro Pérez Alcántara | E10: Programador | F10: Terminado | G10: 5 | H10: 46295 | I10: 46295
A11: T08 | B11: 14 | C11: Herramienta de editor que arma escenas y prefabs (CrearJuego.cs) | D11: Alejandro Pérez Alcántara | E11: Programador | F11: Terminado | G11: 10 | H11: 46296 | I11: 46299
A12: T09 | B12: 6 | C12: Ala de Fuego con Centinelas, Salamandras y Kaelor | D12: Alejandro Pérez Alcántara | E12: Programador | F12: Terminado | G12: 6 | H12: 46297 | I12: 46299
A13: T10 | B13: 8 | C13: Ala de Hielo con Espectros Escarchados, Cristales e Isolde | D13: Alejandro Pérez Alcántara | E13: Programador | F13: Terminado | G13: 6 | H13: 46297 | I13: 46299
A14: T11 | B14: 10 | C14: Ala de Viento con Aves, Golems, plataformas móviles y Threnody | D14: Alejandro Pérez Alcántara | E14: Programador | F14: Terminado | G14: 6 | H14: 46298 | I14: 46299
A15: T12 | B15: 11 | C15: Corazón del Grimorio y Eco de Elenora (4 fases + final) | D15: Alejandro Pérez Alcántara | E15: Programador | F15: Terminado | G15: 8 | H15: 46298 | I15: 46299
... A34: T31 | B34: 25 | C34: Actualizar el libro de producción con el Sprint 2 | D34: Alejandro Pérez Alcántara | E34: Programador | F34: Terminado | G34: 3 | H34: 46302 | I34: 46302
A35: T32 | B35: 14 | C35: Pruebas Alfa de las cinco alas (ver hoja Pruebas Alfa) | D35: Alejandro Pérez Alcántara | E35: Programador | F35: En desarrollo | G35: 6 | H35: 46302
A36: T33 | B36: 24 | C36: Generar el .exe y probarlo en otra computadora | D36: Alejandro Pérez Alcántara | E36: Programador | F36: En desarrollo | G36: 2 | H36: 46308
A37: T34 | B37: 25 | C37: Documento del Producto 2 en Word y PDF con capturas | D37: Alejandro Pérez Alcántara | E37: Programador | F37: Terminado | G37: 6 | H37: 46302 | I37: 46308
A38: T35 | B38: 14 | C38: Sprint Review del Sprint 2 | D38: Alejandro Pérez Alcántara | E38: Programador | F38: Planeado | G38: 1
A39: T36 | B39: 21 | C39: Corregir el acertijo de la caja del Ala de Viento (B-014) | D39: Alejandro Pérez Alcántara | E39: Programador | F39: Terminado | G39: 1 | H39: 46302 | I39: 46302
A40: T37 | B40: 1 | C40: Corregir a Lira flotando sobre el suelo (B-015) | D40: Alejandro Pérez Alcántara | E40: Programador | F40: Terminado | G40: 2 | H40: 46308 | I40: 46308
A41: T38 | B41: 20 | C41: Controles de teclado para laptop (J K L, W para apuntar) | D41: Alejandro Pérez Alcántara | E41: Programador | F41: Terminado | G41: 2 | H41: 46308 | I41: 46308
A42: T39 | B42: 25 | C42: Manual del jugador en PDF | D42: Alejandro Pérez Alcántara | E42: Programador | F42: Terminado | G42: 3 | H42: 46308 | I42: 46308
A43: T40 | B43: 27 | C43: Ayuda para apuntar: el hechizo sigue al enemigo más cercano a la mira (opción en Opciones) | D43: Alejandro Pérez Alcántara | E43: Programador | F43: Terminado | G43: 3 | H43: 46310 | I43: 46310
A44: T41 | B44: 10 | C44: Aves de Tormenta: aviso antes de la picada, descanso después y menos empuje (B-016) | D44: Alejandro Pérez Alcántara | E44: Programador | F44: Terminado | G44: 2 | H44: 46310 | I44: 46310
A45: T42 | B45: 1 | C45: Giro de Lira hacia donde camina con animación (B-017) | D45: Alejandro Pérez Alcántara | E45: Programador | F45: Terminado | G45: 1 | H45: 46310 | I45: 46310
A46: T43 | B46: 23 | C46: Sentido arcano: chispas, tintineo y aviso cerca de secretos (B-018) | D46: Alejandro Pérez Alcántara | E46: Programador | F46: Terminado | G46: 3 | H46: 46310 | I46: 46310
A47: T44 | B47: 19 | C47: 12 efectos de sonido nuevos (lanzar, sin maná, quejido, graznido, caídas, latido, etc.) | D47: Alejandro Pérez Alcántara | E47: Programador | F47: Terminado | G47: 2 | H47: 46310 | I47: 46310
A48: T45 | B48: 27 | C48: Saltar nivel: opción en la pausa y mantener N o L3 + R3 | D48: Alejandro Pérez Alcántara | E48: Programador | F48: Terminado | G48: 2 | H48: 46315 | I48: 46315
A49: T46 | B49: 24 | C49: Compilar la versión 1.0 del .exe y actualizar el manual | D49: Alejandro Pérez Alcántara | E49: Programador | F49: Terminado | G49: 2 | H49: 46315 | I49: 46315
F51: Total horas: | G51: =SUM(G4:G49) -> 187
F52: Terminadas: | G52: =COUNTIF(F4:F49,"Terminado")&" de "&COUNTA(A4:A49) -> 43 de 46
F53: Avance: | G53: =SUMIF(F4:F49,"Terminado",G4:G49)/G51 -> 0.95187166

Sheet Daily Huddle
A1: DAILY HUDDLE - SPRINT 2
A2: Registro de las reuniones diarias (proyecto individual: se responde por escrito al iniciar cada sesión de trabajo).
A3: Fecha | B3: ¿Qué hice desde el último Huddle? | C3: ¿Qué haré hoy? | D3: Impedimentos
A4: 46284 | B4: Sprint Huddle de arranque: cierre del Sprint 1 y revisión del Feature Log. | C4: Ordenar el arte y empezar a importarlo a Unity. | D4: Primera vez armando un proyecto completo en Unity 6.
A5: 46295 | B5: Sprites ordenados; 15 enemigos y jefes y 12 ítems importados. | C5: Código base: ScriptableObjects, PlayerController, Health, SpellCaster, EnemyBase y GameManager. | D5: Muchos sprites con nombres distintos al GDD; se renombraron.
A6: 46299 | B6: Código base y Nivel 1 armado con herramienta de editor. | C6: Generar el juego completo (5 alas, jefes, logros, créditos) y probarlo en Unity. | D6: El escenario se veía plano y las barras del HUD no cargaban su imagen (B-001).
A7: 46300 | B7: Versión 2 con control de PS4, luces 2D y nueva interfaz; historia dentro del juego. | C7: Música, voces, agacharse, niveles más grandes, Opciones, resultados, habilidades 2.11 y acertijos. | D7: Sin sonido (B-003), textos fuera del marco (B-004), final repetido (B-006), portal del Nivel 1 atorado (B-011).
A8: 46302 | B8: Opciones, resultados, habilidades y nueva fuente subidos al repositorio. | C8: Corregir el final de Elenora, agregar capturas y compilación del .exe, actualizar producción. | D8: El final no terminaba al vencer a Elenora (B-012); el panel de depuración se abría con L3 + R3 (B-013); no se abría el pasadizo del Ala de Viento (B-014).
A9: 46308 | B9: Producto 2 completo y probado el final del juego. | C9: Corregir a Lira flotando, controles de teclado para laptop, manual del jugador y generar el .exe. | D9: En la revisión de avance en clase se vio que Lira flota sobre el suelo (B-015).
A10: 46310 | B10: Primer .exe, manual y controles para laptop. Jugué el Ala de Viento con el control de PS4. | C10: Ayuda para apuntar, aves con aviso, giro de Lira, sentido arcano y sonidos nuevos. | D10: Las aves son difíciles de atinar y empujan a Lira al vacío (B-016); Lira no se voltea bien (B-017); no se encuentran los secretos (B-018). Unity se quedaba cargando al abrir el proyecto (se resolvió cerrando procesos).
A11: 46315 | B11: Mejoras del 15 de octubre probadas; en la revisión en clase el juego gustó. | C11: Saltar nivel para la presentación, versión 1.0 del .exe, manual actualizado y preparar el Sprint 3. | D11: Ninguno.

Sheet Project Chart
A1: PROJECT CHART - Estado general del proyecto
A2: Se calcula solo con la columna Estado del Feature Log.
A3: Estado | B3: Features | C3: Porcentaje
A4: Terminado | B4: =COUNTIF('Feature Log'!$C$4:$C$30,A4) -> 24 | C4: =IF(SUM($B$4:$B$7)=0,0,B4/SUM($B$4:$B$7)) -> 0.88888889
A5: En desarrollo | B5: =COUNTIF('Feature Log'!$C$4:$C$30,A5) -> 2 | C5: =IF(SUM($B$4:$B$7)=0,0,B5/SUM($B$4:$B$7)) -> 0.074074074
A6: Planeado | B6: =COUNTIF('Feature Log'!$C$4:$C$30,A6) -> 1 | C6: =IF(SUM($B$4:$B$7)=0,0,B6/SUM($B$4:$B$7)) -> 0.037037037
A7: Sin planear | B7: =COUNTIF('Feature Log'!$C$4:$C$30,A7) -> 0 | C7: =IF(SUM($B$4:$B$7)=0,0,B7/SUM($B$4:$B$7)) -> 0
A8: Total | B8: =SUM(B4:B7) -> 27

Sheet Burn-down Chart
A1: BURN-DOWN CHART - SPRINT 2 (horas restantes)
A2: Ideal: línea recta del total de horas a cero. Real: horas de las tareas que todavía no terminan a esa fecha. Agregar la fórmula de Real en cada nueva fecha.
A3: Fecha | B3: Ideal (hrs) | C3: Real (hrs) | D3: Tareas restantes
A4: 46284 | B4: =ROUND('Sprint Backlog'!$G$51*('Sprint Plan'!$D$5-A4)/('Sprint Plan'!$D$5-'Sprint Plan'!$B$5),1) -> 187 | C4: ='Sprint Backlog'!$G$51-SUMIFS('Sprint Backlog'!$G$4:$G$49,'Sprint Backlog'!$F$4:$F$49,"Terminado",'Sprint Backlog'!$I$4:$I$49,"<="&A4) -> 187 | D4: =COUNTA('Sprint Backlog'!$A$4:$A$49)-COUNTIFS('Sprint Backlog'!$F$4:$F$49,"Terminado",'Sprint Backlog'!$I$4:$I$49,"<="&A4) -> 46
A5: 46288 | B5: =ROUND('Sprint Backlog'!$G$51*('Sprint Plan'!$D$5-A5)/('Sprint Plan'!$D$5-'Sprint Plan'!$B$5),1) -> 168.8 | C5: ='Sprint Backlog'!$G$51-SUMIFS('Sprint Backlog'!$G$4:$G$49,'Sprint Backlog'!$F$4:$F$49,"Terminado",'Sprint Backlog'!$I$4:$I$49,"<="&A5) -> 187 | D5: =COUNTA('Sprint Backlog'!$A$4:$A$49)-COUNTIFS('Sprint Backlog'!$F$4:$F$49,"Terminado",'Sprint Backlog'!$I$4:$I$49,"<="&A5) -> 46
A6: 46291 | B6: =ROUND('Sprint Backlog'!$G$51*('Sprint Plan'!$D$5-A6)/('Sprint Plan'!$D$5-'Sprint Plan'!$B$5),1) -> 155.1 | C6: ='Sprint Backlog'!$G$51-SUMIFS('Sprint Backlog'!$G$4:$G$49,'Sprint Backlog'!$F$4:$F$49,"Terminado",'Sprint Backlog'!$I$4:$I$49,"<="&A6) -> 187 | D6: =COUNTA('Sprint Backlog'!$A$4:$A$49)-COUNTIFS('Sprint Backlog'!$F$4:$F$49,"Terminado",'Sprint Backlog'!$I$4:$I$49,"<="&A6) -> 46
A7: 46295 | B7: =ROUND('Sprint Backlog'!$G$51*('Sprint Plan'!$D$5-A7)/('Sprint Plan'!$D$5-'Sprint Plan'!$B$5),1) -> 136.8 | C7: ='Sprint Backlog'!$G$51-SUMIFS('Sprint Backlog'!$G$4:$G$49,'Sprint Backlog'!$F$4:$F$49,"Terminado",'Sprint Backlog'!$I$4:$I$49,"<="&A7) -> 149 | D7: =COUNTA('Sprint Backlog'!$A$4:$A$49)-COUNTIFS('Sprint Backlog'!$F$4:$F$49,"Terminado",'Sprint Backlog'!$I$4:$I$49,"<="&A7) -> 39
A8: 46299 | B8: =ROUND('Sprint Backlog'!$G$51*('Sprint Plan'!$D$5-A8)/('Sprint Plan'!$D$5-'Sprint Plan'!$B$5),1) -> 118.6 | C8: ='Sprint Backlog'!$G$51-SUMIFS('Sprint Backlog'!$G$4:$G$49,'Sprint Backlog'!$F$4:$F$49,"Terminado",'Sprint Backlog'!$I$4:$I$49,"<="&A8) -> 96 | D8: =COUNTA('Sprint Backlog'!$A$4:$A$49)-COUNTIFS('Sprint Backlog'!$F$4:$F$49,"Terminado",'Sprint Backlog'!$I$4:$I$49,"<="&A8) -> 30
A9: 46300 | B9: =ROUND('Sprint Backlog'!$G$51*('Sprint Plan'!$D$5-A9)/('Sprint Plan'!$D$5-'Sprint Plan'!$B$5),1) -> 114 | C9: ='Sprint Backlog'!$G$51-SUMIFS('Sprint Backlog'!$G$4:$G$49,'Sprint Backlog'!$F$4:$F$49,"Terminado",'Sprint Backlog'!$I$4:$I$49,"<="&A9) -> 46 | D9: =COUNTA('Sprint Backlog'!$A$4:$A$49)-COUNTIFS('Sprint Backlog'!$F$4:$F$49,"Terminado",'Sprint Backlog'!$I$4:$I$49,"<="&A9) -> 18
A10: 46302 | B10: =ROUND('Sprint Backlog'!$G$51*('Sprint Plan'!$D$5-A10)/('Sprint Plan'!$D$5-'Sprint Plan'!$B$5),1) -> 104.9 | C10: ='Sprint Backlog'!$G$51-SUMIFS('Sprint Backlog'!$G$4:$G$49,'Sprint Backlog'!$F$4:$F$49,"Terminado",'Sprint Backlog'!$I$4:$I$49,"<="&A10) -> 37 | D10: =COUNTA('Sprint Backlog'!$A$4:$A$49)-COUNTIFS('Sprint Backlog'!$F$4:$F$49,"Terminado",'Sprint Backlog'!$I$4:$I$49,"<="&A10) -> 14
A11: 46308 | B11: =ROUND('Sprint Backlog'!$G$51*('Sprint Plan'!$D$5-A11)/('Sprint Plan'!$D$5-'Sprint Plan'!$B$5),1) -> 77.5 | C11: ='Sprint Backlog'!$G$51-SUMIFS('Sprint Backlog'!$G$4:$G$49,'Sprint Backlog'!$F$4:$F$49,"Terminado",'Sprint Backlog'!$I$4:$I$49,"<="&A11) -> 24 | D11: =COUNTA('Sprint Backlog'!$A$4:$A$49)-COUNTIFS('Sprint Backlog'!$F$4:$F$49,"Terminado",'Sprint Backlog'!$I$4:$I$49,"<="&A11) -> 10
A12: 46310 | B12: =ROUND('Sprint Backlog'!$G$51*('Sprint Plan'!$D$5-A12)/('Sprint Plan'!$D$5-'Sprint Plan'!$B$5),1) -> 68.4 | C12: ='Sprint Backlog'!$G$51-SUMIFS('Sprint Backlog'!$G$4:$G$49,'Sprint Backlog'!$F$4:$F$49,"Terminado",'Sprint Backlog'!$I$4:$I$49,"<="&A12) -> 13 | D12: =COUNTA('Sprint Backlog'!$A$4:$A$49)-COUNTIFS('Sprint Backlog'!$F$4:$F$49,"Terminado",'Sprint Backlog'!$I$4:$I$49,"<="&A12) -> 5
A13: 46315 | B13: =ROUND('Sprint Backlog'!$G$51*('Sprint Plan'!$D$5-A13)/('Sprint Plan'!$D$5-'Sprint Plan'!$B$5),1) -> 45.6 | C13: ='Sprint Backlog'!$G$51-SUMIFS('Sprint Backlog'!$G$4:$G$49,'Sprint Backlog'!$F$4:$F$49,"Terminado",'Sprint Backlog'!$I$4:$I$49,"<="&A13) -> 9 | D13: =COUNTA('Sprint Backlog'!$A$4:$A$49)-COUNTIFS('Sprint Backlog'!$F$4:$F$49,"Terminado",'Sprint Backlog'!$I$4:$I$49,"<="&A13) -> 3
A14: 46320 | B14: =ROUND('Sprint Backlog'!$G$51*('Sprint Plan'!$D$5-A14)/('Sprint Plan'!$D$5-'Sprint Plan'!$B$5),1) -> 22.8
A15: 46325 | B15: =ROUND('Sprint Backlog'!$G$51*('Sprint Plan'!$D$5-A15)/('Sprint Plan'!$D$5-'Sprint Plan'!$B$5),1) -> 0

Sheet Task Chart
A1: TASK CHART - SPRINT 2 (tareas restantes)
A2: Toma las tareas restantes de la hoja Burn-down Chart.
A3: Fecha | B3: Tareas restantes | C3: Terminadas
A4: ='Burn-down Chart'!A4 -> 46284 | B4: ='Burn-down Chart'!D4 -> 46 | C4: =COUNTA('Sprint Backlog'!$A$4:$A$49)-B4 -> 0
A5: ='Burn-down Chart'!A5 -> 46288 | B5: ='Burn-down Chart'!D5 -> 46 | C5: =COUNTA('Sprint Backlog'!$A$4:$A$49)-B5 -> 0
A6: ='Burn-down Chart'!A6 -> 46291 | B6: ='Burn-down Chart'!D6 -> 46 | C6: =COUNTA('Sprint Backlog'!$A$4:$A$49)-B6 -> 0
A7: ='Burn-down Chart'!A7 -> 46295 | B7: ='Burn-down Chart'!D7 -> 39 | C7: =COUNTA('Sprint Backlog'!$A$4:$A$49)-B7 -> 7
A8: ='Burn-down Chart'!A8 -> 46299 | B8: ='Burn-down Chart'!D8 -> 30 | C8: =COUNTA('Sprint Backlog'!$A$4:$A$49)-B8 -> 16
A9: ='Burn-down Chart'!A9 -> 46300 | B9: ='Burn-down Chart'!D9 -> 18 | C9: =COUNTA('Sprint Backlog'!$A$4:$A$49)-B9 -> 28
A10: ='Burn-down Chart'!A10 -> 46302 | B10: ='Burn-down Chart'!D10 -> 14 | C10: =COUNTA('Sprint Backlog'!$A$4:$A$49)-B10 -> 32
A11: ='Burn-down Chart'!A11 -> 46308 | B11: ='Burn-down Chart'!D11 -> 10 | C11: =COUNTA('Sprint Backlog'!$A$4:$A$49)-B11 -> 36
A12: ='Burn-down Chart'!A12 -> 46310 | B12: ='Burn-down Chart'!D12 -> 5 | C12: =COUNTA('Sprint Backlog'!$A$4:$A$49)-B12 -> 41
A13: ='Burn-down Chart'!A13 -> 46315 | B13: ='Burn-down Chart'!D13 -> 3 | C13: =COUNTA('Sprint Backlog'!$A$4:$A$49)-B13 -> 43

Sheet Buglist
A1: BUGLIST - SPRINT 2 (pruebas Alfa)
A2: Campos de la plantilla de Huddle (GDD 3.6). Se reportan durante las pruebas Alfa de cada versión.
A3: BugID | B3: Descripción | C3: Descripción técnica | D3: Autor | E3: Estado | F3: Featureid | G3: Reportado | H3: Severidad
A4: B-001 | B4: El escenario se veía plano y las barras del HUD no mostraban su imagen. | C4: Los sprites de la UI no estaban asignados en el prefab del HUD y los fondos no tenían capas. | D4: Alejandro Pérez Alcántara | E4: Corregido | F4: 15 | G4: 46299 | H4: Media
A5: B-002 | B5: Faltaban imágenes de la interfaz y las columnas del fondo. | C5: Nombres de archivo distintos entre la carpeta Sprites y las rutas de CrearJuego.cs. | D5: Alejandro Pérez Alcántara | E5: Corregido | F5: 14 | G5: 46300 | H5: Baja
A6: B-003 | B6: No se escuchaba la música ni los efectos. | C6: Ninguna cámara tenía AudioListener. El AudioManager ahora agrega el suyo y quita los de las cámaras. | D6: Alejandro Pérez Alcántara | E6: Corregido | F6: 19 | G6: 46300 | H6: Alta
A7: B-004 | B7: Los textos de Controles y Logros se salían del marco. | C7: El marco ornamentado se estiraba como imagen simple; se cambió por un panel 9-slice (PanelUI). | D7: Alejandro Pérez Alcántara | E7: Corregido | F7: 15 | G7: 46300 | H7: Media
A8: B-005 | B8: El retrato de Lira en el HUD se veía mal dentro del marco. | C8: El sprite completo se mostraba encima del marco; se agregó una máscara circular. | D8: Alejandro Pérez Alcántara | E8: Corregido | F8: 17 | G8: 46300 | H8: Baja
A9: B-006 | B9: Al vencer a Elenora se repetía la batalla final y no salían los créditos. | C9: "Continuar" guardaba el Nivel 5 y no había transición al epílogo; se agregó FinishGame(). | D9: Alejandro Pérez Alcántara | E9: Corregido | F9: 11 | G9: 46300 | H9: Alta
A10: B-007 | B10: Los créditos tardaban unos 15 segundos en aparecer. | C10: El texto empezaba en y = -900, fuera de la pantalla; ahora empieza visible. | D10: Alejandro Pérez Alcántara | E10: Corregido | F10: 18 | G10: 46300 | H10: Media
A11: B-008 | B11: El Modo Archimaga a veces no se activaba. | C11: Cualquier otra tecla reiniciaba la secuencia; ahora solo cuentan las teclas del código. | D11: Alejandro Pérez Alcántara | E11: Corregido | F11: 13 | G11: 46300 | H11: Baja
A12: B-009 | B12: Las voces de los personajes sonaban raras y fuertes. | C12: Síntesis con demasiada aspereza; se suavizó y se bajó el volumen. | D12: Alejandro Pérez Alcántara | E12: Corregido | F12: 19 | G12: 46300 | H12: Baja
A13: B-010 | B13: No se veían las armas de los enemigos. | C13: Los prefabs no tenían el sprite del arma; se creó ArmaEnemigo.cs. | D13: Alejandro Pérez Alcántara | E13: Corregido | F13: 22 | G13: 46300 | H13: Media
A14: B-011 | B14: El juego se quedaba atorado en el portal del Nivel 1 sin mostrar resultados. | C14: Un error en un evento de LevelCompleted cortaba CompleteLevel antes de ShowResults; se protegió con try/catch y Enter/X continúa. | D14: Alejandro Pérez Alcántara | E14: Corregido | F14: 17 | G14: 46300 | H14: Alta
A15: B-012 | B15: Al vencer a Elenora no terminaba el juego. | C15: La secuencia final dependía de que todos los eventos terminaran sin error; ahora hay un respaldo que termina el juego siempre. | D15: Alejandro Pérez Alcántara | E15: Corregido | F15: 11 | G15: 46302 | H15: Alta
... A21: B-018 | B21: No se sabe dónde están las Páginas Perdidas ni los secretos. | C21: No había ninguna pista cerca de ellos. SentidoArcano.cs muestra chispas, un tintineo y un aviso a menos de 7 unidades. | D21: Alejandro Pérez Alcántara | E21: Corregido | F21: 23 | G21: 46310 | H21: Media
D23: Corregidos: | E23: =COUNTIF(E4:E21,"Corregido")&" de "&COUNTA(A4:A21) -> 17 de 18

Sheet Pruebas Alfa
A1: PRUEBAS ALFA - SPRINT 2
A2: Pruebas hechas por el propio equipo al terminar cada versión (Huddle, Producción). Los errores encontrados pasan al Buglist.
A3: ID | B3: Featureid | C3: Caso de prueba | D3: Pasos | E3: Resultado esperado | F3: Resultado obtenido | G3: Estado
A4: PA-01 | B4: 2 | C4: Costo de maná y recarga de cada hechizo | D4: Lanzar el mismo hechizo varias veces seguidas. | E4: No se lanza sin maná suficiente ni antes de que termine la recarga. | F4: Se respeta el costo y la recarga. | G4: Aprobada
A5: PA-02 | B5: 4 | C5: Los hechizos solo dañan lo que tiene IDamageable | D5: Disparar a paredes, plataformas y enemigos. | E5: Solo los enemigos y objetos rompibles reciben daño. | F5: Correcto. | G5: Aprobada
A6: PA-03 | B6: 3 | C6: IA cambia entre patrulla y persecución | D6: Acercarse y alejarse de un Espectro de tinta. | E6: Patrulla lejos de Lira y la persigue dentro de su rango. | F6: Correcto. | G6: Aprobada
A7: PA-04 | B7: 20 | C7: Control de PS4 por Bluetooth | D7: Jugar el Nivel 1 completo solo con el control. | E7: Todas las acciones responden y el control vibra al recibir daño. | F7: Correcto. | G7: Aprobada
A8: PA-05 | B8: 19 | C8: Música y efectos al iniciar | D8: Abrir el juego desde el menú principal. | E8: Se escucha la música del menú y los sonidos de los botones. | F8: Sin sonido (B-003). Corregido. | G8: Aprobada
A9: PA-06 | B9: 17 | C9: Cambio de nivel con pantalla de resultados | D9: Terminar el Nivel 1 y entrar al portal. | E9: Aparece la pantalla de resultados y luego carga el Nivel 2. | F9: Se quedaba atorado (B-011). Corregido. | G9: Aprobada
A10: PA-07 | B10: 13 | C10: Modo Archimaga | D10: Escribir F, H, V, A y Enter; con control L1 + R1 + Triángulo. | E10: Aparece el aviso y Lira no gasta maná ni recibe daño. | F10: Fallaba a veces (B-008). Corregido. | G10: Aprobada
A11: PA-08 | B11: 16 | C11: Pantalla de Opciones | D11: Cambiar volúmenes, pantalla completa y vibración; salir y volver a entrar. | E11: Los cambios se aplican y se guardan. | F11: Funciona en el editor. | G11: Aprobada
A12: PA-09 | B12: 21 | C12: Fuego quema las zarzas | D12: Lanzar Arcano y luego Fuego a las zarzas del Ala de Fuego. | E12: Solo el Fuego las quema y se abre el pasadizo. | G12: Pendiente
A13: PA-10 | B13: 21 | C13: Hielo congela al tercer golpe | D13: Pegarle tres veces seguidas con Hielo a un enemigo. | E13: El enemigo se pinta de azul y no se mueve por 2.5 s. | G13: Pendiente
A14: PA-11 | B14: 21 | C14: Viento: planear y empujar la caja | D14: Mantener saltar al caer; empujar la caja del Ala de Viento hasta la placa. | E14: Lira cae lento; la caja abre la puerta rúnica. | F14: No se podía abrir (B-014). Corregido, falta probar. | G14: Pendiente
A15: PA-12 | B15: 11 | C15: Final del juego | D15: Derrotar al Eco de Elenora y leer su diálogo. | E15: ¡VICTORIA!, epílogo y créditos; al final regresa al menú. | F15: No terminaba (B-012). Corregido: sale ¡VICTORIA!, epílogo y créditos. | G15: Aprobada
A16: PA-13 | B16: 23 | C16: Páginas Perdidas y salas secretas | D16: Recoger las 3 páginas del Nivel 1 y romper un muro agrietado. | E16: Cada página da +5 de vida máxima; el muro revela la sala. | G16: Pendiente
A17: PA-14 | B17: 24 | C17: Build .exe | D17: Compilar con el menú Ecos del Grimorio y abrir el .exe. | E17: El juego abre en pantalla completa y se puede jugar de inicio a fin. | F17: Compila sin errores (150 MB). Falta probarlo en otra computadora. | G17: Pendiente
A18: PA-15 | B18: 1 | C18: Lira pisa el suelo | D18: Caminar y detenerse sobre el suelo y las plataformas de cada ala. | E18: Los pies de Lira tocan la superficie, sin espacio. | F18: Flotaba (B-015). Corregido. | G18: Aprobada
A19: PA-16 | B19: 27 | C19: Saltar nivel | D19: En cada ala mantener N (o L3 + R3) 1.5 s, y probar Pausa > Saltar nivel. | E19: Pasa a la siguiente ala con el hechizo que tocaba; en el Corazón pasa al final. No da logros. | G19: Pendiente
A20: PA-17 | B20: 27 | C20: Ayuda para apuntar | D20: Disparar a las Aves de Tormenta con y sin la opción activada. | E20: Con la opción, el hechizo sigue al ave; sin ella, va en línea recta. | G20: Pendiente
F22: Aprobadas: | G22: =COUNTIF(G4:G20,"Aprobada")&" de "&COUNTA(A4:A20) -> 10 de 17

Sheet Matriz GDD
A1: COHERENCIA ENTRE EL GDD Y EL BACKLOG
A2: Cada requisito del documento de diseño tiene su feature y sus tareas. El estado toma el del primer feature de la lista.
A3: Sección GDD | B3: Requisito del documento de diseño | C3: Featureid | D3: Tareas | E3: Estado
A4: 2.1 / 2.3 | B4: Acertijos ambientales; cada hechizo abre rutas bloqueadas | C4: 21 | D4: T27 | E4: =IFERROR(INDEX('Feature Log'!$C$4:$C$30,MATCH(VALUE(LEFT(C4,FIND(",",C4&",")-1)),'Feature Log'!$A$4:$A$30,0)),"") -> Terminado
A5: 2.4 | B5: Cámara lateral con seguimiento suave | C5: 1 | D5: T03 | E5: =IFERROR(INDEX('Feature Log'!$C$4:$C$30,MATCH(VALUE(LEFT(C5,FIND(",",C5&",")-1)),'Feature Log'!$A$4:$A$30,0)),"") -> Terminado
A6: 2.4 | B6: Teclado y control (New Input System) | C6: 20 | D6: T16 | E6: =IFERROR(INDEX('Feature Log'!$C$4:$C$30,MATCH(VALUE(LEFT(C6,FIND(",",C6&",")-1)),'Feature Log'!$A$4:$A$30,0)),"") -> Terminado
A7: 2.4 | B7: Guardado automático en puntos de control | C7: 15 | D7: T07 | E7: =IFERROR(INDEX('Feature Log'!$C$4:$C$30,MATCH(VALUE(LEFT(C7,FIND(",",C7&",")-1)),'Feature Log'!$A$4:$A$30,0)),"") -> Terminado
A8: 2.5 | B8: Estados: Menú, Juego, Pausa, Logros, Game Over, Créditos | C8: 15 | D8: T07, T14 | E8: =IFERROR(INDEX('Feature Log'!$C$4:$C$30,MATCH(VALUE(LEFT(C8,FIND(",",C8&",")-1)),'Feature Log'!$A$4:$A$30,0)),"") -> Terminado
A9: 2.5 / 2.6 | B9: Pantalla de Opciones | C9: 16 | D9: T25 | E9: =IFERROR(INDEX('Feature Log'!$C$4:$C$30,MATCH(VALUE(LEFT(C9,FIND(",",C9&",")-1)),'Feature Log'!$A$4:$A$30,0)),"") -> Terminado
A10: 2.6 | B10: HUD: vida, maná, hechizo equipado y fragmentos | C10: 17 | D10: T14, T26 | E10: =IFERROR(INDEX('Feature Log'!$C$4:$C$30,MATCH(VALUE(LEFT(C10,FIND(",",C10&",")-1)),'Feature Log'!$A$4:$A$30,0)),"") -> Terminado
A11: 2.7 | B11: Cinco niveles (alas) con su elenco y guardián | C11: 6, 8, 10, 11 | D11: T09 a T12 | E11: =IFERROR(INDEX('Feature Log'!$C$4:$C$30,MATCH(VALUE(LEFT(C11,FIND(",",C11&",")-1)),'Feature Log'!$A$4:$A$30,0)),"") -> Terminado
A12: 2.8 | B12: Progreso: hechizos, fragmentos y coleccionables | C12: 23 | D12: T20 | E12: =IFERROR(INDEX('Feature Log'!$C$4:$C$30,MATCH(VALUE(LEFT(C12,FIND(",",C12&",")-1)),'Feature Log'!$A$4:$A$30,0)),"") -> Terminado
A13: 2.9 / 2.10 | B13: Personajes y enemigos | C13: 3, 11 | D13: T06, T22 | E13: =IFERROR(INDEX('Feature Log'!$C$4:$C$30,MATCH(VALUE(LEFT(C13,FIND(",",C13&",")-1)),'Feature Log'!$A$4:$A$30,0)),"") -> Terminado
A14: 2.11 | B14: Habilidades: Fuego quema, Hielo congela, Viento planea y empuja | C14: 5, 7, 9, 21 | D14: T23, T27 | E14: =IFERROR(INDEX('Feature Log'!$C$4:$C$30,MATCH(VALUE(LEFT(C14,FIND(",",C14&",")-1)),'Feature Log'!$A$4:$A$30,0)),"") -> Terminado
A15: 2.12 | B15: Armas de los enemigos | C15: 22 | D15: T24 | E15: =IFERROR(INDEX('Feature Log'!$C$4:$C$30,MATCH(VALUE(LEFT(C15,FIND(",",C15&",")-1)),'Feature Log'!$A$4:$A$30,0)),"") -> Terminado
... A23: 2.4 / 2.6 | B23: Ayudas al jugador y opción de ayuda para apuntar | C23: 27 | D23: T40, T43, T45 | E23: =IFERROR(INDEX('Feature Log'!$C$4:$C$30,MATCH(VALUE(LEFT(C23,FIND(",",C23&",")-1)),'Feature Log'!$A$4:$A$30,0)),"") -> Terminado

Sheet Sprint Review
A1: SPRINT REVIEW - SPRINT 2 (avance al 20 de octubre de 2026)
A3: Meta del sprint | B3: Juego completo jugable en Unity con las cinco alas, jefes, logros y Modo Archimaga, listo para pruebas Alfa.
A4: Tareas terminadas | B4: =COUNTIF('Sprint Backlog'!$F$4:$F$49,"Terminado")&" de "&COUNTA('Sprint Backlog'!$A$4:$A$49) -> 43 de 46
A5: Horas terminadas | B5: =SUMIF('Sprint Backlog'!$F$4:$F$49,"Terminado",'Sprint Backlog'!$G$4:$G$49)&" de "&'Sprint Backlog'!$G$51&" hrs" -> 178 de 187 hrs
A6: Features terminados | B6: =COUNTIF('Feature Log'!$C$4:$C$30,"Terminado")&" de "&COUNTA('Feature Log'!$A$4:$A$30) -> 24 de 27
A7: Bugs corregidos | B7: =COUNTIF(Buglist!$E$4:$E$21,"Corregido")&" de "&COUNTA(Buglist!$A$4:$A$21) -> 17 de 18
A8: Pruebas Alfa aprobadas | B8: =COUNTIF('Pruebas Alfa'!$G$4:$G$20,"Aprobada")&" de "&COUNTA('Pruebas Alfa'!$A$4:$A$20) -> 10 de 17
A9: Demostración | B9: Partida con el .exe y el control de PS4: diálogo con la Maestra Sable, combate, sala secreta, pantalla de resultados, Opciones y saltar nivel para mostrar las cinco alas y el final.
A10: ¿Qué salió bien? | B10: La herramienta de editor permite reconstruir todas las escenas en un clic. El código con herencia (EnemyBase, BossController) hizo rápido agregar enemigos y jefes. Se adelantaron los features de los Sprints 3 y 4.
A11: ¿Qué salió mal? | B11: Varias fallas solo aparecieron al jugar con el control (sonido, textos fuera del marco, final del juego) o en la revisión en clase (Lira flotando). El Ala de Viento quedó muy difícil por las aves. El Burn-down muestra que la mayor parte del trabajo se concentró en pocos días.
A12: Ajustes para el Sprint 3 | B12: Sesiones más cortas y repartidas. Probar cada ala completa antes de agregar contenido nuevo. Pruebas Beta con compañeros usando el .exe.
A13: Fecha de cierre | B13: 30 de octubre de 2026 (entrega del Producto 2)

Sheet Pruebas Beta
A1: PRUEBAS BETA - SPRINT 3 (31 oct - 20 nov, 2026)
A2: Una fila por cada persona que prueba el juego, copiada de su formato de Pruebas Beta. Calificaciones del 1 (malo) al 5 (excelente). Los errores nuevos se pasan al Buglist con su BugID.
A3: ID | B3: Fecha | C3: Jugador(a) | D3: Tipo | E3: Jugó con | F3: Ala a la que llegó | G3: Minutos jugados | H3: Diversión (1-5) | I3: Controles claros (1-5) | J3: Dificultad (1-5) | K3: Lo que más le gustó | L3: Lo que no entendió | M3: Errores (BugID) | N3: Estado
A4: PB-01
A5: PB-02
A6: PB-03
A7: PB-04
A8: PB-05
A9: PB-06
A10: PB-07
A11: PB-08
A12: PB-09
A13: PB-10
A14: PB-11
A15: PB-12
... A18: PB-15
F20: Personas que probaron: | H20: =COUNTA(C4:C18) -> 0
F21: Promedio diversión: | H21: =IF(COUNT(H4:H18)=0,"",ROUND(AVERAGE(H4:H18),1))
F22: Promedio controles: | H22: =IF(COUNT(I4:I18)=0,"",ROUND(AVERAGE(I4:I18),1))
F23: Promedio dificultad: | H23: =IF(COUNT(J4:J18)=0,"",ROUND(AVERAGE(J4:J18),1))
F24: Terminaron el juego: | H24: =COUNTIF(F4:F18,"Terminó el juego") -> 0
